erico_image_processing/__init__.py
erico_image_processing/processing/__init__.py
erico_image_processing/processing/combination.py
erico_image_processing/processing/transformation.py
erico_image_processing/utils/__init__.py
erico_image_processing/utils/io.py
erico_image_processing/utils/plot.py
Erico_Image_Processing-0.0.1.dist-info/METADATA
Erico_Image_Processing-0.0.1.dist-info/WHEEL
Erico_Image_Processing-0.0.1.dist-info/top_level.txt
Erico_Image_Processing-0.0.1.dist-info/RECORD
