Metadata-Version: 2.1
Name: Erico-Image-Processing
Version: 0.0.1
Summary: ## Descrição
Home-page: https://github.com/EricoCoutoJr/image-processing-package.git
Author: Erico Couto Jr.
Author-email: erico.coutojr@gmail.com
Requires-Python: >=3.8
Requires-Dist: numpy ==1.21.0
Requires-Dist: scikit-image ==0.24.0
Requires-Dist: matplotlib ==3.9.0
